LICENSE.md
README.md
setup.py
qics/__init__.py
qics/_version.py
qics/io.py
qics/model.py
qics/point.py
qics/solver.py
qics/vectorize.py
qics.egg-info/PKG-INFO
qics.egg-info/SOURCES.txt
qics.egg-info/dependency_links.txt
qics.egg-info/requires.txt
qics.egg-info/top_level.txt
qics/_stepper/__init__.py
qics/_stepper/kktsolver.py
qics/_stepper/nonsym.py
qics/_stepper/sym.py
qics/_utils/__init__.py
qics/_utils/gradient.py
qics/_utils/linalg.py
qics/cones/__init__.py
qics/cones/base.py
qics/cones/entropy/__init__.py
qics/cones/entropy/classentr.py
qics/cones/entropy/classrelentr.py
qics/cones/entropy/quantcondentr.py
qics/cones/entropy/quantentr.py
qics/cones/entropy/quantkeydist.py
qics/cones/entropy/quantrelentr.py
qics/cones/perspective/__init__.py
qics/cones/perspective/opperspecepi.py
qics/cones/perspective/opperspectr.py
qics/cones/renyi/__init__.py
qics/cones/renyi/quasientr.py
qics/cones/renyi/renyientr.py
qics/cones/renyi/sandquasientr.py
qics/cones/renyi/sandrenyientr.py
qics/cones/symmetric/__init__.py
qics/cones/symmetric/nonnegorthant.py
qics/cones/symmetric/possemidefinite.py
qics/cones/symmetric/secondorder.py
qics/quantum/__init__.py
qics/quantum/entropy.py
qics/quantum/operator.py
qics/quantum/random.py
tests/test_cones.py
tests/test_examples.py
tests/test_quantum.py