Metadata-Version: 2.1
Name: qics
Version: 1.1.2
Summary: Conic solver for quantum information theory
Author: Kerry He, James Saunderson, and Hamza Fawzi
Author-email: he.kerry.k@gmail.com, james.saunderson@monash.edu, h.fawzi@damtp.cam.ac.uk
License: MIT
Project-URL: Source, https://github.com/kerry-he/qics
Project-URL: Documentation, https://qics.readthedocs.io/en/latest/
Requires-Python: >=3.8
License-File: LICENSE.md
Requires-Dist: numpy
Requires-Dist: scipy
Requires-Dist: numba
